fabhacks
