Metadata-Version: 1.0
Name: Fabhacks
Version: 0.1.2
Summary: Some Fabric-based hacks
Home-page: http://github.com/EDITD/fabhacks
Author: Nick @ EDITD
Author-email: dev@editd.com
License: UNKNOWN
Platform: UNKNOWN
